nomad_dos_fingerprints/DOSfingerprint.py
nomad_dos_fingerprints/__init__.py
nomad_dos_fingerprints/grid.py
nomad_dos_fingerprints/plotting.py
nomad_dos_fingerprints/similarity.py
nomad_dos_fingerprints-1.0.2.dist-info/LICENSE
nomad_dos_fingerprints-1.0.2.dist-info/METADATA
nomad_dos_fingerprints-1.0.2.dist-info/WHEEL
nomad_dos_fingerprints-1.0.2.dist-info/top_level.txt
nomad_dos_fingerprints-1.0.2.dist-info/RECORD
