Metadata-Version: 2.1
Name: nomad-dos-fingerprints
Version: 1.0.2
Summary: An implementation of DOS fingerprints for the NOMAD Laboratory.
Home-page: https://gitlab.mpcdf.mpg.de/nomad-lab/nomad-dos-fingerprints
Author: The NOMAD Authors
Author-email: kuban@physik.hu-berlin.de
License: Apache-2.0
Project-URL: homepage, https://github.com/nomad-coe/nomad-dos-fingerprints
License-File: LICENSE
Requires-Dist: nomad-lab >=1.3.6.dev1
Provides-Extra: dev
Requires-Dist: mypy ==1.0.1 ; extra == 'dev'
Requires-Dist: pytest ==3.10.0 ; extra == 'dev'
Requires-Dist: pytest-timeout ==1.4.2 ; extra == 'dev'
Requires-Dist: pytest-cov ==2.7.1 ; extra == 'dev'
Requires-Dist: ruff ==0.1.4 ; extra == 'dev'
Requires-Dist: uv >=0.2.35 ; extra == 'dev'
